kitools/__init__.py
kitools/data_type.py
kitools/data_type_template.py
kitools/data_uri.py
kitools/env.py
kitools/exceptions.py
kitools/ki_project.py
kitools/ki_project_resource.py
kitools/remote_entity.py
kitools/sys_path.py
kitools/utils.py
kitools/data_adapters/__init__.py
kitools/data_adapters/base_adapter.py
kitools/data_adapters/synapse/__init__.py
kitools/data_adapters/synapse/synapse_adapter.py
kitools/data_adapters/synapse/synapse_remote_entity.py
kitools-0.0.2.dist-info/LICENSE
kitools-0.0.2.dist-info/METADATA
kitools-0.0.2.dist-info/NOTICE
kitools-0.0.2.dist-info/WHEEL
kitools-0.0.2.dist-info/top_level.txt
kitools-0.0.2.dist-info/RECORD
