Metadata-Version: 2.1
Name: kitools
Version: 0.0.2
Summary: ki tools package
Home-page: https://github.com/ki-tools/kitools-py
Author: Patrick Stout, Ryan Hafen, Sergey Feldman
Author-email: pstout@prevagroup.com, rhafen@gmail.com, sergey@data-cowboys.com
License: Apache2
Platform: UNKNOWN
Classifier: License :: OSI Approved :: Apache Software License
Classifier: Operating System :: POSIX
Classifier: Operating System :: MacOS :: MacOS X
Classifier: Operating System :: Microsoft :: Windows
Classifier: Programming Language :: Python
Classifier: Programming Language :: Python :: 3.5
Classifier: Programming Language :: Python :: 3.6
Classifier: Programming Language :: Python :: 3.7
Classifier: Intended Audience :: Science/Research
Classifier: Intended Audience :: Developers
Requires-Dist: synapseclient (<2.0.0,>=1.9.2)
Requires-Dist: beautifultable (<1.0.0,>=0.7.0)
